nltk_theme/__init__.py
nltk_theme/footer.html
nltk_theme/layout.html
nltk_theme/menu.html
nltk_theme/search.html
nltk_theme/searchinput.html
nltk_theme/theme.conf
nltk_theme/static/css/custom.css
nltk_theme/static/css/nltk_theme.css
nltk_theme/static/img/favicon-16x16.png
nltk_theme/static/img/favicon-32x32.png
nltk_theme-2.0.6.dist-info/LICENSE
nltk_theme-2.0.6.dist-info/METADATA
nltk_theme-2.0.6.dist-info/WHEEL
nltk_theme-2.0.6.dist-info/entry_points.txt
nltk_theme-2.0.6.dist-info/top_level.txt
nltk_theme-2.0.6.dist-info/RECORD
