Metadata-Version: 2.1
Name: nltk-theme
Version: 2.0.6
Summary: Clean, minimalist Sphinx theme for NLTK, based on Insegel
Home-page: https://github.com/tomaarsen/nltk_theme
Author: Mika Naylor (Autophagy), Tom Aarsen
Author-email: cubiegamedev@gmail.com
License: MIT
Platform: UNKNOWN
Classifier: Framework :: Sphinx
Classifier: Framework :: Sphinx :: Theme
Classifier: Development Status :: 2 - Pre-Alpha
Classifier: License :: OSI Approved :: MIT License
Classifier: Environment :: Console
Classifier: Environment :: Web Environment
Classifier: Intended Audience :: Developers
Classifier: Programming Language :: Python :: 3
Classifier: Programming Language :: Python :: 3.6
Classifier: Programming Language :: Python :: 3.7
Classifier: Programming Language :: Python :: 3.8
Classifier: Programming Language :: Python :: 3.9
Classifier: Operating System :: OS Independent
Classifier: Topic :: Documentation
Classifier: Topic :: Software Development :: Documentation
